blist/__init__.py
blist/api.py
blist/errors.py
blist/models.py
blist/webhooks.py
blistpy-0.1.3.dist-info/LICENSE.md
blistpy-0.1.3.dist-info/METADATA
blistpy-0.1.3.dist-info/WHEEL
blistpy-0.1.3.dist-info/top_level.txt
blistpy-0.1.3.dist-info/RECORD
